pykulgap/__init__.py
pykulgap/helpers.py
pykulgap/io.py
pykulgap/pipelines.py
pykulgap/plotting.py
pykulgap/classes/CancerModel.py
pykulgap/classes/ExperimentalCondition.py
pykulgap/classes/TreatmentResponseExperiment.py
pykulgap/classes/__init__.py
pykulgap-0.0.9.dist-info/LICENSE
pykulgap-0.0.9.dist-info/METADATA
pykulgap-0.0.9.dist-info/WHEEL
pykulgap-0.0.9.dist-info/top_level.txt
pykulgap-0.0.9.dist-info/RECORD
