Metadata-Version: 2.1
Name: pykulgap
Version: 0.0.9
Summary: Functions for statistical analysis of treatment response curves in patient derived xenograph (PDX) models of cancer.
Home-page: https://github.com/bhklab/pyKuLGaP/
Author: Janosch Ortmann, Christopher Eeles, Benjamin Haibe-Kains
Author-email: janosch.ortmann@gmail.com, christopher.eeles@uhnresearch.ca, benjamin.haibe.kains@utoronto.ca
License: MIT
Platform: UNKNOWN
